[
  {
    "subject_slug": "current-affairs-general-knowledge",
    "difficulty": "easy",
    "question_text": "Which arm of government is responsible for interpreting the law in Nigeria?",
    "option_a": "Executive",
    "option_b": "Judiciary",
    "option_c": "Legislature",
    "option_d": "Civil Service Commission",
    "correct_option": "B",
    "explanation": "The judiciary interprets the law and resolves legal disputes within Nigeria's constitutional system.",
    "reference_note": "Nigerian constitutional structure",
    "source_note": "Development seed question - not official exam content",
    "status": "published"
  },
  {
    "subject_slug": "current-affairs-general-knowledge",
    "difficulty": "medium",
    "question_text": "The main purpose of a national budget is to",
    "option_a": "appoint ministers",
    "option_b": "set court judgments",
    "option_c": "plan government revenue and expenditure",
    "option_d": "conduct elections",
    "correct_option": "C",
    "explanation": "A national budget outlines how government expects to raise revenue and allocate spending for a period.",
    "reference_note": "Public finance and governance basics",
    "source_note": "Development seed question - not official exam content",
    "status": "published"
  },
  {
    "subject_slug": "current-affairs-general-knowledge",
    "difficulty": "medium",
    "question_text": "Which institution is primarily responsible for conducting federal elections in Nigeria?",
    "option_a": "Federal Civil Service Commission",
    "option_b": "Independent National Electoral Commission",
    "option_c": "National Assembly Service Commission",
    "option_d": "Code of Conduct Tribunal",
    "correct_option": "B",
    "explanation": "INEC is the body established to organize and supervise federal and state elections in Nigeria.",
    "reference_note": "INEC and Nigerian electoral system",
    "source_note": "Development seed question - not official exam content",
    "status": "published"
  }
]
